pyTermUI/__init__.py
pyTermUI/button.py
pyTermUI/checkbox.py
pyTermUI/colors.py
pyTermUI/element.py
pyTermUI/position.py
pyTermUI/region.py
pyTermUI/text.py
pyTermUI/textbox.py
pyTermUI/ui.py
pyTermUI/Toolkit/asciiart.py
pyTermUI/Toolkit/hover.py
pyTermUI/Toolkit/taskhandler.py
pyTermUI-1.2.3.dist-info/LICENSE
pyTermUI-1.2.3.dist-info/METADATA
pyTermUI-1.2.3.dist-info/WHEEL
pyTermUI-1.2.3.dist-info/top_level.txt
pyTermUI-1.2.3.dist-info/RECORD
